{"version": 0.6, "generator": "Overpass API 0.7.62.11 87bfad18", "osm3s": {"timestamp_osm_base": "2026-07-01T02:14:01Z", "copyright": "The data included in this document is from www.openstreetmap.org. The data is made available under ODbL."}, "elements": [{"type": "node", "id": 506849960, "lat": -22.9681155, "lon": -43.1834769, "tags": {"amenity": "hospital", "healthcare": "hospital", "name": "Hospital Galdino Campos"}}, {"type": "node", "id": 1620388977, "lat": -22.9658029, "lon": -43.1899568}, {"type": "node", "id": 1620388979, "lat": -22.9651786, "lon": -43.1907074}, {"type": "node", "id": 1620388981, "lat": -22.9654176, "lon": -43.1904893}, {"type": "node", "id": 1620388983, "lat": -22.9652672, "lon": -43.1903862}, {"type": "node", "id": 1620388987, "lat": -22.9654552, "lon": -43.1905379}, {"type": "node", "id": 1620388990, "lat": -22.9654958, "lon": -43.190237}, {"type": "node", "id": 1620388991, "lat": -22.9654689, "lon": -43.1902022}, {"type": "node", "id": 1620388993, "lat": -22.9659259, "lon": -43.1901158}, {"type": "node", "id": 3759045769, "lat": -22.966844, "lon": -43.186807, "tags": {"addr:city": "Rio de Janeiro", "addr:housenumber": "129", "addr:postcode": "22031-071", "addr:street": "Rua Siqueira Campos", "amenity": "hospital", "healthcare": "hospital", "name": "UPA Unidade de Pronto Atendimento"}}, {"type": "node", "id": 4803812951, "lat": -22.9668721, "lon": -43.1886804, "tags": {"entrance": "yes"}}, {"type": "node", "id": 4803812952, "lat": -22.9666725, "lon": -43.1887911}, {"type": "node", "id": 4803812953, "lat": -22.966353, "lon": -43.1883759}, {"type": "node", "id": 5607454783, "lat": -22.9725531, "lon": -43.1927254}, {"type": "node", "id": 5607460930, "lat": -22.9723434, "lon": -43.1928842}, {"type": "node", "id": 5607460931, "lat": -22.972401, "lon": -43.1926578}, {"type": "node", "id": 5607460932, "lat": -22.9724726, "lon": -43.1929507}, {"type": "node", "id": 5607460933, "lat": -22.972377, "lon": -43.1931155}, {"type": "node", "id": 5607460934, "lat": -22.9722477, "lon": -43.1930441}, {"type": "node", "id": 5607460935, "lat": -22.9722694, "lon": -43.1929589}, {"type": "node", "id": 5607460936, "lat": -22.9724143, "lon": -43.1930279}, {"type": "node", "id": 5607460937, "lat": -22.9724019, "lon": -43.1926462}, {"type": "node", "id": 5607460938, "lat": -22.9725069, "lon": -43.1923746}, {"type": "node", "id": 5607460939, "lat": -22.9726266, "lon": -43.1924353}, {"type": "node", "id": 5607460940, "lat": -22.9725421, "lon": -43.1927032}, {"type": "node", "id": 5607514745, "lat": -22.9721104, "lon": -43.1930203}, {"type": "node", "id": 5607514746, "lat": -22.9721707, "lon": -43.1930495}, {"type": "node", "id": 5607514747, "lat": -22.9722029, "lon": -43.1929327}, {"type": "node", "id": 5607514748, "lat": -22.9721631, "lon": -43.1929116}, {"type": "node", "id": 5607514749, "lat": -22.9721943, "lon": -43.1928801}, {"type": "node", "id": 5607514750, "lat": -22.9720954, "lon": -43.1927247}, {"type": "node", "id": 5607514751, "lat": -22.9719932, "lon": -43.19281}, {"type": "node", "id": 5607514752, "lat": -22.9720362, "lon": -43.1929093}, {"type": "node", "id": 5607514753, "lat": -22.972026, "lon": -43.1927826}, {"type": "node", "id": 5607514758, "lat": -22.9720729, "lon": -43.1927435}, {"type": "node", "id": 5619829693, "lat": -22.9715909, "lon": -43.1908783, "tags": {"addr:street": "Rua Cinco de Julho", "amenity": "hospital", "healthcare": "hospital", "name": "Cl\u00ednica 5 de Julho"}}, {"type": "node", "id": 5773766121, "lat": -22.9650798, "lon": -43.1905798}, {"type": "node", "id": 7761133009, "lat": -22.966043, "lon": -43.1902672}, {"type": "node", "id": 7761133010, "lat": -22.9657331, "lon": -43.1905501}, {"type": "node", "id": 7761133011, "lat": -22.9656126, "lon": -43.1903943}, {"type": "node", "id": 7761133014, "lat": -22.9651176, "lon": -43.1905228}, {"type": "node", "id": 7761133015, "lat": -22.9651278, "lon": -43.190536}, {"type": "node", "id": 9590558435, "lat": -22.9669579, "lon": -43.1886026}, {"type": "node", "id": 9590558437, "lat": -22.9666325, "lon": -43.1882281}, {"type": "node", "id": 9590558438, "lat": -22.9664377, "lon": -43.1883302}, {"type": "node", "id": 9590558439, "lat": -22.9665004, "lon": -43.188415}, {"type": "node", "id": 9590558440, "lat": -22.9666654, "lon": -43.1882711}, {"type": "node", "id": 9590558441, "lat": -22.9667687, "lon": -43.1887743}, {"type": "node", "id": 9590558442, "lat": -22.9667367, "lon": -43.1887328}, {"type": "node", "id": 9590558443, "lat": -22.9669181, "lon": -43.1885508}, {"type": "node", "id": 9590558444, "lat": -22.9669615, "lon": -43.1885114}, {"type": "node", "id": 9590558445, "lat": -22.9667102, "lon": -43.1881844}, {"type": "node", "id": 9875941247, "lat": -22.9666411, "lon": -43.188498}, {"type": "node", "id": 9875941248, "lat": -22.9667122, "lon": -43.188434}, {"type": "node", "id": 9875941249, "lat": -22.966792, "lon": -43.1885388}, {"type": "node", "id": 9875941250, "lat": -22.9667208, "lon": -43.1886027}, {"type": "node", "id": 10005305678, "lat": -22.9724676, "lon": -43.1927254, "tags": {"addr:city": "Rio de Janeiro", "addr:country": "BR", "addr:housenumber": "21A", "addr:postcode": "22061-000", "addr:street": "Travessa Frederico Pamplona", "addr:suburb": "Copacabana", "amenity": "hospital", "healthcare": "hospital", "name": "Hospital S\u00e3o Lucas (Exames De Imagem)"}}, {"type": "node", "id": 10005340469, "lat": -22.9723124, "lon": -43.1930798}, {"type": "way", "id": 148993687, "nodes": [1620388979, 1620388981, 1620388987, 7761133011, 7761133010, 7761133009, 1620388993, 1620388977, 1620388990, 1620388991, 1620388983, 7761133014, 7761133015, 5773766121, 1620388979], "tags": {"amenity": "hospital", "building": "hospital", "contact:phone": "+55 21 2545 3600", "emergency": "yes", "healthcare": "hospital", "name": "Copa D'or", "operator:type": "private", "url": "http://www.copador.com.br/"}}, {"type": "way", "id": 488009638, "nodes": [4803812952, 4803812953, 9590558438, 9590558439, 9590558440, 9590558437, 9590558445, 9590558444, 9590558443, 9590558435, 4803812951, 9590558441, 9590558442, 4803812952]}, {"type": "way", "id": 586974150, "nodes": [5607460930, 5607460931, 5607454783, 5607460932, 5607460930], "tags": {"addr:city": "Rio de Janeiro", "addr:housenumber": "21B", "addr:postcode": "22061-000", "addr:street": "Travessa Frederico Pamplona", "addr:suburb": "Copacabana", "amenity": "hospital", "emergency": "yes", "healthcare": "hospital", "name": "Hospital S\u00e3o Lucas (Emergencia)"}}, {"type": "way", "id": 586974152, "nodes": [5607460933, 10005340469, 5607460934, 5607460935, 5607460936, 5607460933], "tags": {"addr:city": "Rio de Janeiro", "addr:housenumber": "32C", "addr:postcode": "22061-000", "addr:street": "Travessa Frederico Pamplona", "addr:suburb": "Copacabana", "amenity": "hospital", "emergency": "yes", "healthcare": "hospital", "name": "Hospital Sao Lucas (Ambulancia)"}}, {"type": "way", "id": 586974155, "nodes": [5607460937, 5607460940, 5607460939, 5607460938, 5607460937], "tags": {"addr:city": "Rio de Janeiro", "addr:housenumber": "21C", "addr:postcode": "22061-000", "addr:street": "Travessa Frederico Pamplona", "addr:suburb": "Copacabana", "amenity": "hospital", "emergency": "yes", "healthcare": "hospital", "name": "Hospital Sao Lucas", "ref:CNES": "7474059", "ref:vatin": "BR60884855001630"}}, {"type": "way", "id": 586980034, "nodes": [5607514745, 5607514746, 5607514747, 5607514748, 5607514749, 5607514750, 5607514758, 5607514753, 5607514751, 5607514752, 5607514745], "tags": {"addr:city": "Rio de Janeiro", "addr:housenumber": "32B", "addr:postcode": "22061-000", "addr:street": "Travessa Frederico Pamplona", "addr:suburb": "Copacabana", "amenity": "hospital", "emergency": "yes", "healthcare": "hospital", "name": "Hospital S\u00e3o Lucas (Recepcao)"}}, {"type": "way", "id": 1077042743, "nodes": [9875941250, 9875941249, 9875941248, 9875941247, 9875941250]}, {"type": "relation", "id": 14336242, "members": [{"type": "way", "ref": 1077042743, "role": "inner"}, {"type": "way", "ref": 488009638, "role": "outer"}], "tags": {"amenity": "hospital", "building": "hospital", "healthcare": "hospital", "name": "Copastar", "operator": "Rede D'or", "type": "multipolygon", "wikidata": "Q130529679"}}]}